README.rst
setup.cfg
setup.py
akilib/__init__.py
akilib.egg-info/PKG-INFO
akilib.egg-info/SOURCES.txt
akilib.egg-info/dependency_links.txt
akilib.egg-info/top_level.txt
akilib/edison/AKI_AQM1248A.py
akilib/edison/AKI_GPIO_SC1602BSLB.py
akilib/edison/AKI_GPIO_SG12864ASLB.py
akilib/edison/AKI_I2C_AQM0802A.py
akilib/edison/AKI_I2C_BM280.py
akilib/edison/AKI_I2C_HDC1000.py
akilib/edison/AKI_I2C_L3GD20.py
akilib/edison/AKI_I2C_LIS3DH.py
akilib/edison/AKI_I2C_LPS25H.py
akilib/edison/AKI_I2C_MCP23017.py
akilib/edison/AKI_I2C_OLED.py
akilib/edison/AKI_I2C_S11059.py
akilib/edison/AKI_I2C_SO1602AWYB.py
akilib/edison/AKI_SG12864ASLB.py
akilib/edison/AKI_SPI_AQM1248A.py
akilib/edison/MCP23017.py
akilib/edison/__init__.py
akilib/edison/test.py
akilib/raspberrypi/AKI_GPIO_SC1602BSLB.py
akilib/raspberrypi/AKI_I2C_ACM1602N1.py
akilib/raspberrypi/AKI_I2C_ADT7410.py
akilib/raspberrypi/AKI_I2C_AQM0802A.py
akilib/raspberrypi/AKI_I2C_AQM1602A.py
akilib/raspberrypi/AKI_I2C_HDC1000.py
akilib/raspberrypi/AKI_I2C_LPS25H.py
akilib/raspberrypi/AKI_I2C_MCP3425.py
akilib/raspberrypi/AKI_I2C_PCA9685.py
akilib/raspberrypi/AKI_I2C_S11059.py
akilib/raspberrypi/AKI_I2C_SHT31.py
akilib/raspberrypi/AKI_SC1602BSLB.py
akilib/raspberrypi/__init__.py
akilib/edison/AKI_AQM1248A.py
akilib/edison/AKI_GPIO_SC1602BSLB.py
akilib/edison/AKI_GPIO_SG12864ASLB.py
akilib/edison/AKI_I2C_AQM0802A.py
akilib/edison/AKI_I2C_BM280.py
akilib/edison/AKI_I2C_HDC1000.py
akilib/edison/AKI_I2C_L3GD20.py
akilib/edison/AKI_I2C_LIS3DH.py
akilib/edison/AKI_I2C_LPS25H.py
akilib/edison/AKI_I2C_MCP23017.py
akilib/edison/AKI_I2C_OLED.py
akilib/edison/AKI_I2C_S11059.py
akilib/edison/AKI_I2C_SO1602AWYB.py
akilib/edison/AKI_SG12864ASLB.py
akilib/edison/AKI_SPI_AQM1248A.py
akilib/edison/MCP23017.py
akilib/edison/__init__.py
akilib/edison/test.py
akilib/raspberrypi/AKI_GPIO_SC1602BSLB.py
akilib/raspberrypi/AKI_I2C_ACM1602N1.py
akilib/raspberrypi/AKI_I2C_ADT7410.py
akilib/raspberrypi/AKI_I2C_AQM0802A.py
akilib/raspberrypi/AKI_I2C_AQM1602A.py
akilib/raspberrypi/AKI_I2C_HDC1000.py
akilib/raspberrypi/AKI_I2C_LPS25H.py
akilib/raspberrypi/AKI_I2C_MCP3425.py
