Metadata-Version: 1.0
Name: akilib
Version: 2.1.6
Summary: This Library is Hardware Library. and You can buy parts in Japan Akihabara .
Home-page: https://github.com/nonNoise/akilib
Author:  Yuta KItagami
Author-email: kitagami@artifactnoise.com
License: MIT License
Keywords: Hardware,Edison,RaspberryPi,Raspberry,IoT,akilib
Platform: Linux
